<?xml version="1.0" encoding="utf-8" ?>
<dwsync>
<file name="activity-report-widget.css" server="ftp.ezyro.com//htdocs/" local="131345027454237563" remote="131344499400000000" Dst="0" />
<file name="colorbox.css" server="ftp.ezyro.com//htdocs/" local="131345027459157454" remote="131344499400000000" Dst="0" />
<file name="diff.css" server="ftp.ezyro.com//htdocs/" local="131345027466466096" remote="131344499400000000" Dst="0" />
<file name="dt_table.css" server="ftp.ezyro.com//htdocs/" local="131345027467441757" remote="131344499400000000" Dst="0" />
<file name="fullLog.css" server="ftp.ezyro.com//htdocs/" local="131345027471411578" remote="131344499400000000" Dst="0" />
<file name="iptraf.css" server="ftp.ezyro.com//htdocs/" local="131345027524124083" remote="131344499400000000" Dst="0" />
<file name="jquery-ui-timepicker-addon.css" server="ftp.ezyro.com//htdocs/" local="131345027528763735" remote="131344499400000000" Dst="0" />
<file name="jquery-ui.structure.min.css" server="ftp.ezyro.com//htdocs/" local="131345027539261448" remote="131344499400000000" Dst="0" />
<file name="jquery-ui.min.css" server="ftp.ezyro.com//htdocs/" local="131345027540187703" remote="131344499400000000" Dst="0" />
<file name="jquery-ui.theme.min.css" server="ftp.ezyro.com//htdocs/" local="131345027543382401" remote="131344499400000000" Dst="0" />
<file name="phpinfo.css" server="ftp.ezyro.com//htdocs/" local="131345027555405192" remote="131344499400000000" Dst="0" />
<file name="select2.min.css" server="ftp.ezyro.com//htdocs/" local="131345027557496777" remote="131344499400000000" Dst="0" />
<file name="main.css" server="ftp.ezyro.com//htdocs/" local="131345027562558399" remote="131344499400000000" Dst="0" />
<file name="wf-adminbar.css" server="ftp.ezyro.com//htdocs/" local="131345027571094083" remote="131344499400000000" Dst="0" />
<file name="wordfenceBox.css" server="ftp.ezyro.com//htdocs/" local="131345027576472642" remote="131344499400000000" Dst="0" />
<file name="wf-ionicons.css" server="ftp.ezyro.com//htdocs/" local="131345027577058038" remote="131344499400000000" Dst="0" />
</dwsync>